hello_world_ogk/__init__.py
hello_world_ogk/hello_world.py
hello_world_ogk-0.1.7.dist-info/LICENSE
hello_world_ogk-0.1.7.dist-info/METADATA
hello_world_ogk-0.1.7.dist-info/WHEEL
hello_world_ogk-0.1.7.dist-info/top_level.txt
hello_world_ogk-0.1.7.dist-info/RECORD
