Metadata-Version: 2.2
Name: hello-world-ogk
Version: 0.1.7
Summary: A hello-world package for GitHub
Author-email: Kenta Ogawa <gakenshizu1199@gmail.com>
Project-URL: Homepage, https://github.com/ogaken1104/hello-world
Project-URL: Repository, https://github.com/ogaken1104/hello-world.git
Requires-Python: >=3.10
License-File: LICENSE
